interceptor/__init__.py
intxr-0.28.0.dist-info/LICENSE
intxr-0.28.0.dist-info/METADATA
intxr-0.28.0.dist-info/WHEEL
intxr-0.28.0.dist-info/entry_points.txt
intxr-0.28.0.dist-info/top_level.txt
intxr-0.28.0.dist-info/RECORD
